easysound/__init__.py
easysound/play.py
easysound/rec.py
easysound-1.0.3.dist-info/LICENSE
easysound-1.0.3.dist-info/METADATA
easysound-1.0.3.dist-info/WHEEL
easysound-1.0.3.dist-info/top_level.txt
easysound-1.0.3.dist-info/RECORD
