Metadata-Version: 2.1
Name: easysound
Version: 1.0.3
Summary: A simple, easy sound programming in Python.
Home-page: https://github.com/ericzzer/Easy_Sound
Author: Eric Zeng
Author-email: ericchufengzeng@163.com
License: MIT
Platform: UNKNOWN
Classifier: License :: OSI Approved :: MIT License
Classifier: Programming Language :: Python
Classifier: Programming Language :: Python :: 3
Classifier: Programming Language :: Python :: 3.6
Classifier: Programming Language :: Python :: Implementation :: CPython
Classifier: Programming Language :: Python :: Implementation :: PyPy
Requires-Python: >=3.6.0
Requires-Dist: pysound
